{
  "generated_at_utc": "2026-07-11T13:13:01.905202+00:00",
  "target_date": "2026-07-10",
  "graded_rows": 143,
  "binary_rows": 143,
  "overall": {
    "n": 143,
    "units": 11.636,
    "roi": 0.0814,
    "win_rate": 0.5664
  },
  "thresholds": {
    "probability": [
      {
        "threshold": 0.52,
        "n": 36,
        "units": 0.273,
        "roi": 0.0076,
        "win_rate": 0.5278
      },
      {
        "threshold": 0.54,
        "n": 36,
        "units": 0.273,
        "roi": 0.0076,
        "win_rate": 0.5278
      },
      {
        "threshold": 0.56,
        "n": 36,
        "units": 0.273,
        "roi": 0.0076,
        "win_rate": 0.5278
      },
      {
        "threshold": 0.58,
        "n": 36,
        "units": 0.273,
        "roi": 0.0076,
        "win_rate": 0.5278
      },
      {
        "threshold": 0.6,
        "n": 36,
        "units": 0.273,
        "roi": 0.0076,
        "win_rate": 0.5278
      },
      {
        "threshold": 0.62,
        "n": 36,
        "units": 0.273,
        "roi": 0.0076,
        "win_rate": 0.5278
      },
      {
        "threshold": 0.65,
        "n": 36,
        "units": 0.273,
        "roi": 0.0076,
        "win_rate": 0.5278
      }
    ],
    "edge_pct": [
      {
        "threshold": 2,
        "n": 36,
        "units": 0.273,
        "roi": 0.0076,
        "win_rate": 0.5278
      },
      {
        "threshold": 3,
        "n": 36,
        "units": 0.273,
        "roi": 0.0076,
        "win_rate": 0.5278
      },
      {
        "threshold": 4,
        "n": 36,
        "units": 0.273,
        "roi": 0.0076,
        "win_rate": 0.5278
      },
      {
        "threshold": 5,
        "n": 36,
        "units": 0.273,
        "roi": 0.0076,
        "win_rate": 0.5278
      },
      {
        "threshold": 6,
        "n": 36,
        "units": 0.273,
        "roi": 0.0076,
        "win_rate": 0.5278
      },
      {
        "threshold": 8,
        "n": 36,
        "units": 0.273,
        "roi": 0.0076,
        "win_rate": 0.5278
      },
      {
        "threshold": 10,
        "n": 36,
        "units": 0.273,
        "roi": 0.0076,
        "win_rate": 0.5278
      }
    ],
    "ev_pct": [
      {
        "threshold": 1,
        "n": 53,
        "units": 4.273,
        "roi": 0.0806,
        "win_rate": 0.566
      },
      {
        "threshold": 2,
        "n": 52,
        "units": 3.364,
        "roi": 0.0647,
        "win_rate": 0.5577
      },
      {
        "threshold": 3,
        "n": 51,
        "units": 4.364,
        "roi": 0.0856,
        "win_rate": 0.5686
      },
      {
        "threshold": 4,
        "n": 49,
        "units": 2.545,
        "roi": 0.0519,
        "win_rate": 0.551
      },
      {
        "threshold": 5,
        "n": 46,
        "units": 3.636,
        "roi": 0.0791,
        "win_rate": 0.5652
      },
      {
        "threshold": 7.5,
        "n": 45,
        "units": 2.727,
        "roi": 0.0606,
        "win_rate": 0.5556
      },
      {
        "threshold": 10,
        "n": 40,
        "units": 2.0,
        "roi": 0.05,
        "win_rate": 0.55
      }
    ],
    "history_games": [
      {
        "threshold": 2,
        "n": 0,
        "units": 0,
        "roi": null,
        "win_rate": null
      },
      {
        "threshold": 3,
        "n": 0,
        "units": 0,
        "roi": null,
        "win_rate": null
      },
      {
        "threshold": 5,
        "n": 0,
        "units": 0,
        "roi": null,
        "win_rate": null
      },
      {
        "threshold": 7,
        "n": 0,
        "units": 0,
        "roi": null,
        "win_rate": null
      },
      {
        "threshold": 10,
        "n": 0,
        "units": 0,
        "roi": null,
        "win_rate": null
      }
    ],
    "book_count": [
      {
        "threshold": 1,
        "n": 0,
        "units": 0,
        "roi": null,
        "win_rate": null
      },
      {
        "threshold": 2,
        "n": 0,
        "units": 0,
        "roi": null,
        "win_rate": null
      },
      {
        "threshold": 3,
        "n": 0,
        "units": 0,
        "roi": null,
        "win_rate": null
      }
    ],
    "final_score": [
      {
        "threshold": 55,
        "n": 36,
        "units": 0.273,
        "roi": 0.0076,
        "win_rate": 0.5278
      },
      {
        "threshold": 60,
        "n": 36,
        "units": 0.273,
        "roi": 0.0076,
        "win_rate": 0.5278
      },
      {
        "threshold": 65,
        "n": 36,
        "units": 0.273,
        "roi": 0.0076,
        "win_rate": 0.5278
      },
      {
        "threshold": 70,
        "n": 36,
        "units": 0.273,
        "roi": 0.0076,
        "win_rate": 0.5278
      },
      {
        "threshold": 75,
        "n": 36,
        "units": 0.273,
        "roi": 0.0076,
        "win_rate": 0.5278
      },
      {
        "threshold": 80,
        "n": 36,
        "units": 0.273,
        "roi": 0.0076,
        "win_rate": 0.5278
      },
      {
        "threshold": 85,
        "n": 0,
        "units": 0,
        "roi": null,
        "win_rate": null
      },
      {
        "threshold": 90,
        "n": 0,
        "units": 0,
        "roi": null,
        "win_rate": null
      }
    ]
  },
  "feature_importance": [
    {
      "feature": "consensus_score",
      "samples": 143,
      "correlation": -0.0799,
      "importance": 0.0799
    },
    {
      "feature": "simulation_probability",
      "samples": 36,
      "correlation": -0.0638,
      "importance": 0.0638
    },
    {
      "feature": "final_score",
      "samples": 36,
      "correlation": -0.0328,
      "importance": 0.0328
    },
    {
      "feature": "ev_pct",
      "samples": 143,
      "correlation": 0.019,
      "importance": 0.019
    },
    {
      "feature": "edge_pct",
      "samples": 36,
      "correlation": -0.0162,
      "importance": 0.0162
    },
    {
      "feature": "book_count",
      "samples": 36,
      "correlation": 0.0,
      "importance": 0.0
    },
    {
      "feature": "history_games",
      "samples": 36,
      "correlation": 0.0,
      "importance": 0.0
    }
  ],
  "learned_weights": {
    "ev_pct": 1.0
  },
  "performance_by_stat": [
    {
      "stat": "PTS",
      "n": 33,
      "units": 5.182,
      "roi": 0.157,
      "win_rate": 0.6061
    },
    {
      "stat": "REB",
      "n": 21,
      "units": 1.909,
      "roi": 0.0909,
      "win_rate": 0.5714
    },
    {
      "stat": "PRA",
      "n": 20,
      "units": -0.909,
      "roi": -0.0455,
      "win_rate": 0.5
    },
    {
      "stat": "PR",
      "n": 19,
      "units": -1.818,
      "roi": -0.0957,
      "win_rate": 0.4737
    },
    {
      "stat": "3PM",
      "n": 16,
      "units": -2.636,
      "roi": -0.1648,
      "win_rate": 0.4375
    },
    {
      "stat": "PA",
      "n": 15,
      "units": 0.273,
      "roi": 0.0182,
      "win_rate": 0.5333
    },
    {
      "stat": "AST",
      "n": 12,
      "units": 7.091,
      "roi": 0.5909,
      "win_rate": 0.8333
    },
    {
      "stat": "RA",
      "n": 7,
      "units": 2.545,
      "roi": 0.3636,
      "win_rate": 0.7143
    }
  ],
  "recommendations": {
    "minimum_probability": 0.56,
    "minimum_edge_pct": 5,
    "minimum_ev_pct": 2,
    "maximum_ev_pct": 20,
    "minimum_history_games": 5,
    "minimum_books": 2
  },
  "learning_status": "calibrating"
}